CHANGELOG.rst
CODE_OF_CONDUCT.rst
CONTRIBUTING.rst
CONTRIBUTORS.rst
LICENSE
README.rst
THANKS.rst
TODO.rst
bash-completion/blackhole-completion.bash
blackhole/__init__.py
blackhole/__main__.py
blackhole/application.py
blackhole/child.py
blackhole/config.py
blackhole/control.py
blackhole/daemon.py
blackhole/exceptions.py
blackhole/logs.py
blackhole/protocols.py
blackhole/smtp.py
blackhole/streams.py
blackhole/supervisor.py
blackhole/utils.py
blackhole/worker.py
example.conf
blackhole-2.1.19.dist-info/entry_points.txt
blackhole-2.1.19.dist-info/LICENSE
blackhole-2.1.19.dist-info/WHEEL
blackhole-2.1.19.dist-info/METADATA
blackhole-2.1.19.dist-info/RECORD
